{"name":"tweetust","counts":{"unstable":54,"stable":69,"unmarked":307},"submodules":[{"name":"clients","counts":{"unstable":10,"stable":10,"unmarked":183},"submodules":[{"name":"direct_messages","counts":{"unstable":1,"stable":1,"unmarked":36},"submodules":[]},{"name":"search","counts":{"unstable":5,"stable":5,"unmarked":23},"submodules":[]},{"name":"statuses","counts":{"unstable":3,"stable":3,"unmarked":117},"submodules":[]}]},{"name":"conn","counts":{"unstable":2,"stable":6,"unmarked":20},"submodules":[{"name":"application_only_authenticator","counts":{"unstable":1,"stable":3,"unmarked":3},"submodules":[]},{"name":"oauth_authenticator","counts":{"unstable":1,"stable":3,"unmarked":5},"submodules":[]}]},{"name":"models","counts":{"unstable":31,"stable":43,"unmarked":65},"submodules":[{"name":"direct_messages","counts":{"unstable":1,"stable":3,"unmarked":3},"submodules":[]},{"name":"entities","counts":{"unstable":12,"stable":12,"unmarked":25},"submodules":[]},{"name":"error","counts":{"unstable":4,"stable":2,"unmarked":4},"submodules":[]},{"name":"places","counts":{"unstable":2,"stable":4,"unmarked":5},"submodules":[]},{"name":"search","counts":{"unstable":2,"stable":2,"unmarked":5},"submodules":[]},{"name":"tweets","counts":{"unstable":6,"stable":13,"unmarked":13},"submodules":[]},{"name":"users","counts":{"unstable":1,"stable":3,"unmarked":3},"submodules":[]}]},{"name":"oauth","counts":{"unstable":4,"stable":4,"unmarked":16},"submodules":[]},{"name":"oauth2","counts":{"unstable":4,"stable":4,"unmarked":16},"submodules":[]}]}